AUTHORS.rst
MANIFEST.in
README.md
requirements_dev.txt
setup.cfg
setup.py
askanna_cli/__init__.py
askanna_cli/__main__.py
askanna_cli/artifact.py
askanna_cli/createproject.py
askanna_cli/deploy.py
askanna_cli/exceptions.py
askanna_cli/jobrun_manifest.py
askanna_cli/login.py
askanna_cli/logout.py
askanna_cli/mock.py
askanna_cli/package_download.py
askanna_cli/payload.py
askanna_cli/push.py
askanna_cli/run.py
askanna_cli/tool.py
askanna_cli/utils.py
askanna_cli.egg-info/PKG-INFO
askanna_cli.egg-info/SOURCES.txt
askanna_cli.egg-info/dependency_links.txt
askanna_cli.egg-info/entry_points.txt
askanna_cli.egg-info/not-zip-safe
askanna_cli.egg-info/requires.txt
askanna_cli.egg-info/top_level.txt
askanna_cli/core/__init__.py
askanna_cli/core/apiclient.py
askanna_cli/core/config.py
askanna_cli/core/download.py
askanna_cli/core/session.py
askanna_cli/core/upload.py
askanna_cli/core/user.py
askanna_cli/core/vault.py
docs/Makefile
docs/authors.rst
docs/conf.py
docs/contributing.rst
docs/history.rst
docs/index.rst
docs/installation.rst
docs/readme.rst
docs/usage.rst
tests/__init__.py
tests/base.py
tests/test_cli_login.py
tests/test_cli_logout.py
tests/test_cli_push.py