Metadata-Version: 2.1
Name: askanna-cli
Version: 0.1.0
Summary: AskAnna Command line and library interface
Home-page: https://gitlab.askanna.io/askanna/askanna-cli
Author: AskAnna
Author-email: devops@askanna.io
License: UNKNOWN
Keywords: askanna
Platform: UNKNOWN
Classifier: Development Status :: 2 - Pre-Alpha
Classifier: Intended Audience :: Developers
Classifier: Natural Language :: English
Classifier: Programming Language :: Python :: 3
Classifier: Programming Language :: Python :: 3.5
Classifier: Programming Language :: Python :: 3.6
Classifier: Programming Language :: Python :: 3.7
Classifier: Programming Language :: Python :: 3.8
Requires-Python: >=3.5
